giga_openai_test/__init__.py
giga_openai_test-0.1.0.dist-info/METADATA
giga_openai_test-0.1.0.dist-info/WHEEL
giga_openai_test-0.1.0.dist-info/RECORD
